nonebot_plugin_whois/__init__.py
nonebot_plugin_whois-1.0.5.dist-info/METADATA
nonebot_plugin_whois-1.0.5.dist-info/WHEEL
nonebot_plugin_whois-1.0.5.dist-info/licenses/LICENSE
nonebot_plugin_whois-1.0.5.dist-info/RECORD
