Metadata-Version: 2.4
Name: nonebot-plugin-whois
Version: 1.0.5
Summary: 一个Nonebot2插件用于查询域名的whois信息
License: GPL-3.0
License-File: LICENSE
Keywords: nonebot2,domain,whois
Author: Maizi
Author-email: maizicncn@gmail.com
Requires-Python: >=3.8,<4.0
Classifier: License :: OSI Approved :: GNU General Public License v3 (GPLv3)
Classifier: Programming Language :: Python :: 3
Classifier: Programming Language :: Python :: 3.8
Classifier: Programming Language :: Python :: 3.9
Classifier: Programming Language :: Python :: 3.10
Classifier: Programming Language :: Python :: 3.11
Classifier: Programming Language :: Python :: 3.12
Classifier: Programming Language :: Python :: 3.13
Classifier: Programming Language :: Python :: 3.14
Requires-Dist: httpx (>=0.26.0,<1.0.0)
Requires-Dist: nonebot-adapter-onebot (>=2.0.0,<3.0.0)
Requires-Dist: nonebot2 (>=2.2.1,<3.0.0)
Project-URL: Documentation, https://github.com/Maizi-G/nonebot-plugin-whois#readme
Project-URL: Homepage, https://github.com/Maizi-G/nonebot-plugin-whois
Project-URL: Repository, https://github.com/Maizi-G/nonebot-plugin-whois
